bbutils/__init__.py
bbutils/scripts/server.py
bbutils/static/extract_submission_file.js
bbutils/templates/index.html
makefile/__init__.py
ta_tooling/__init__.py
ta_tooling/__main__.py
ta_tooling/cli.py
ta_tooling/scripts/__init__.py
ta_tooling/scripts/next.sh
ta_tooling-0.3.3.dist-info/LICENSE
ta_tooling-0.3.3.dist-info/METADATA
ta_tooling-0.3.3.dist-info/WHEEL
ta_tooling-0.3.3.dist-info/entry_points.txt
ta_tooling-0.3.3.dist-info/top_level.txt
ta_tooling-0.3.3.dist-info/RECORD
