Metadata-Version: 2.1
Name: ta-tooling
Version: 0.3.3
Summary: Various tools for teaching assistants working with Blackboard
Author-email: Krerkkiat Chusap <kc555014@ohio.edu>
License: MIT
Project-URL: Home, https://github.com/krerkkiat/ta-tooling
Keywords: Blackboard
Classifier: Development Status :: 2 - Pre-Alpha
Classifier: License :: OSI Approved :: MIT License
Classifier: Programming Language :: Python :: 3.10
Requires-Python: >=3.10
License-File: LICENSE
Requires-Dist: click
Requires-Dist: flask
Requires-Dist: flask-cors
Requires-Dist: selenium
Requires-Dist: requests
Requires-Dist: pandas
Requires-Dist: python-dotenv
